sleepydatapeek.py
sleepydatapeek_toolchain/command_logic.py
sleepydatapeek_toolchain/params.py
sleepydatapeek_toolchain/utils.py
sleepydatapeek-1.7.3.dist-info/LICENSE
sleepydatapeek-1.7.3.dist-info/METADATA
sleepydatapeek-1.7.3.dist-info/WHEEL
sleepydatapeek-1.7.3.dist-info/RECORD
