Metadata-Version: 2.3
Name: sleepydatapeek
Version: 1.7.3
Summary: Peek at local datafiles fast!
License: GNU GENERAL PUBLIC LICENSE
Keywords: pandas,data,analysis,cli
Author: Isaac Yep
Author-email: anthonybenchyep@gmail.com
Requires-Python: >=3.10
Classifier: License :: Other/Proprietary License
Classifier: Programming Language :: Python :: 3
Classifier: Programming Language :: Python :: 3.10
Classifier: Programming Language :: Python :: 3.11
Classifier: Programming Language :: Python :: 3.12
Classifier: Programming Language :: Python :: 3.13
Requires-Dist: PyPDF2 (>=3.0.1,<4.0.0)
Requires-Dist: pandas (>=1.5.1,<2.0.0)
Requires-Dist: pyarrow (>=11.0,<12.0.0)
Requires-Dist: tabulate (>=0.9,<1.0.0)
Requires-Dist: typer (>=0.15,<1.0.0)
Project-URL: Repository, https://github.com/anthonybench/datapeek
